darkgmailapi/__init__.py
darkgmailapi/darkgmailapi.py
darkgmailapi-0.0.4.dist-info/LICENSE
darkgmailapi-0.0.4.dist-info/METADATA
darkgmailapi-0.0.4.dist-info/WHEEL
darkgmailapi-0.0.4.dist-info/top_level.txt
darkgmailapi-0.0.4.dist-info/RECORD
