Metadata-Version: 2.1
Name: darkgmailapi
Version: 0.0.4
Summary: A package to access the google gmail api
Author-email: Dark_Eden <darkedenc9@gmail.com>
Project-URL: Homepage, https://github.com/DarkEden-coding/darkgmailapi
Project-URL: Bug Tracker, https://github.com/DarkEden-coding/darkgmailapi/issues
Classifier: Programming Language :: Python :: 3
Classifier: License :: OSI Approved :: MIT License
Classifier: Operating System :: OS Independent
Requires-Python: >=3.7
License-File: LICENSE
